{
  "hash": "f4819a48",
  "configHash": "8fb27815",
  "lockfileHash": "0ad88a12",
  "browserHash": "22547779",
  "optimized": {
    "react": {
      "src": "../../node_modules/react/index.js",
      "file": "react.js",
      "fileHash": "e124048f",
      "needsInterop": true
    },
    "react-dom/client": {
      "src": "../../node_modules/react-dom/client.js",
      "file": "react-dom_client.js",
      "fileHash": "5169318d",
      "needsInterop": true
    }
  },
  "chunks": {
    "chunk-GFWMZNU4": {
      "file": "chunk-GFWMZNU4.js"
    }
  }
}